gnome_extensions_cli/__init__.py
gnome_extensions_cli/cli.py
gnome_extensions_cli/commands/__init__.py
gnome_extensions_cli/commands/disable.py
gnome_extensions_cli/commands/enable.py
gnome_extensions_cli/commands/install.py
gnome_extensions_cli/commands/list_.py
gnome_extensions_cli/commands/preferences.py
gnome_extensions_cli/commands/search.py
gnome_extensions_cli/commands/show.py
gnome_extensions_cli/commands/uninstall.py
gnome_extensions_cli/commands/update.py
gnome_extensions_cli/dbus.py
gnome_extensions_cli/filesystem.py
gnome_extensions_cli/icons.py
gnome_extensions_cli/manager.py
gnome_extensions_cli/schema.py
gnome_extensions_cli/store.py
gnome_extensions_cli/utils.py
gnome_extensions_cli-0.10.7.dist-info/METADATA
gnome_extensions_cli-0.10.7.dist-info/WHEEL
gnome_extensions_cli-0.10.7.dist-info/entry_points.txt
gnome_extensions_cli-0.10.7.dist-info/licenses/LICENSE
gnome_extensions_cli-0.10.7.dist-info/RECORD
