Metadata-Version: 2.4
Name: gnome-extensions-cli
Version: 0.10.7
Summary: Command line tool to manage your Gnome Shell extensions
License: Apache-2.0
License-File: LICENSE
Author: Sébastien MB
Author-email: seb@essembeh.org
Requires-Python: >=3.8,<4.0
Classifier: Development Status :: 4 - Beta
Classifier: License :: OSI Approved :: Apache Software License
Classifier: Programming Language :: Python :: 3
Classifier: Programming Language :: Python :: 3.8
Classifier: Programming Language :: Python :: 3.9
Classifier: Programming Language :: Python :: 3.10
Classifier: Programming Language :: Python :: 3.11
Classifier: Programming Language :: Python :: 3.12
Classifier: Programming Language :: Python :: 3.13
Classifier: Programming Language :: Python :: 3.14
Classifier: Topic :: Utilities
Requires-Dist: colorama (>=0.4.5,<0.5.0)
Requires-Dist: packaging (>=23.0,<24.0)
Requires-Dist: pydantic (>=2.3.0,<3.0.0)
Requires-Dist: requests (>=2.28.1,<3.0.0)
Requires-Dist: tqdm (>=4.66.1,<5.0.0)
Project-URL: Homepage, https://github.com/essembeh/gnome-extensions-cli
